pytest_fly/__init__.py
pytest_fly/__main__.py
pytest_fly/__version__.py
pytest_fly/const.py
pytest_fly/guid.py
pytest_fly/interfaces.py
pytest_fly/logger.py
pytest_fly/main.py
pytest_fly/paths.py
pytest_fly/preferences.py
pytest_fly/db/__init__.py
pytest_fly/db/db.py
pytest_fly/gui/__init__.py
pytest_fly/gui/gui_main.py
pytest_fly/gui/gui_util.py
pytest_fly/gui/about_tab/__init__.py
pytest_fly/gui/about_tab/about.py
pytest_fly/gui/about_tab/project_info.py
pytest_fly/gui/configuration_tab/__init__.py
pytest_fly/gui/configuration_tab/configuration.py
pytest_fly/gui/graph_tab/__init__.py
pytest_fly/gui/graph_tab/graph_tab.py
pytest_fly/gui/graph_tab/progress_bar.py
pytest_fly/gui/run_tab/__init__.py
pytest_fly/gui/run_tab/control_pushbutton.py
pytest_fly/gui/run_tab/control_window.py
pytest_fly/gui/run_tab/parallelism_control_box.py
pytest_fly/gui/run_tab/run_mode_control_box.py
pytest_fly/gui/run_tab/run_tab.py
pytest_fly/gui/run_tab/status_window.py
pytest_fly/gui/run_tab/view_coverage.py
pytest_fly/gui/table_tab/__init__.py
pytest_fly/gui/table_tab/table_tab.py
pytest_fly/platform/__init__.py
pytest_fly/platform/os.py
pytest_fly/platform/platform_info.py
pytest_fly/pytest_runner/__init__.py
pytest_fly/pytest_runner/const.py
pytest_fly/pytest_runner/coverage.py
pytest_fly/pytest_runner/process_monitor.py
pytest_fly/pytest_runner/pytest_process.py
pytest_fly/pytest_runner/pytest_runner.py
pytest_fly/pytest_runner/test_list.py
pytest_fly/pytest_runner/utilization.py
pytest_fly-0.1.3.dist-info/METADATA
pytest_fly-0.1.3.dist-info/WHEEL
pytest_fly-0.1.3.dist-info/licenses/LICENSE
pytest_fly-0.1.3.dist-info/RECORD
