Metadata-Version: 2.4
Name: pytest-fly
Version: 0.1.3
Summary: pytest runner and observer
Project-URL: Home, https://github.com/jamesabel/pytest-fly
Project-URL: Repository, https://github.com/jamesabel/pytest-fly
Project-URL: Documentation, https://github.com/jamesabel/pytest-fly#readme
Author-email: James Abel <j@abel.co>
Maintainer-email: James Abel <j@abel.co>
License: 
License-File: LICENSE
Keywords: observer,pytest,testing
Classifier: Development Status :: 3 - Alpha
Classifier: Framework :: Pytest
Classifier: Intended Audience :: Developers
Classifier: License :: OSI Approved :: MIT License
Classifier: Operating System :: OS Independent
Classifier: Programming Language :: Python
Classifier: Programming Language :: Python :: 3 :: Only
Classifier: Programming Language :: Python :: 3.12
Classifier: Topic :: Software Development :: Testing
Requires-Python: >=3.12
Requires-Dist: attrs
Requires-Dist: balsa
Requires-Dist: coverage
Requires-Dist: hashy
Requires-Dist: humanize
Requires-Dist: ismain
Requires-Dist: msqlite
Requires-Dist: numpy
Requires-Dist: platformdirs
Requires-Dist: pref
Requires-Dist: psutil
Requires-Dist: py-cpuinfo
Requires-Dist: pyside6
Requires-Dist: pytest
Requires-Dist: tobool
Requires-Dist: typeguard
Requires-Dist: uuid6
Requires-Dist: watchdog
